{"cameraMode":{"drawMode":0,"name":"Shaded","section":"Shading Mode"},"sceneLighting":true,"audioPlay":false,"sceneViewState":{"showFog":true,"showMaterialUpdate":false,"showSkybox":true,"showFlares":true,"showImageEffects":true,"showParticleSystems":true},"in2DMode":false,"pivot":{"x":0.02868504263460636,"y":1.55596923828125,"z":0.990956723690033},"rotation":{"x":-0.1148926243185997,"y":-0.0010305979521945119,"z":0.00009841917199082673,"w":-0.9934176802635193},"size":1.412017583847046,"orthographic":false}